<hudson.model.Queue_-State>
  <counter>2123</counter>
  <items>
    <hudson.model.Queue_-BlockedItem>
      <actions>
        <hudson.model.CauseAction>
          <causeBag class="linked-hash-map">
            <entry>
              <hudson.model.Cause_-UpstreamCause>
                <upstreamProject>jenkins-job-generator-trigger</upstreamProject>
                <upstreamUrl>job/jenkins-job-generator-trigger/</upstreamUrl>
                <upstreamBuild>22</upstreamBuild>
                <upstreamCauses>
                  <hudson.triggers.SCMTrigger_-SCMTriggerCause />
                </upstreamCauses>
              </hudson.model.Cause_-UpstreamCause>
              <int>1</int>
            </entry>
            <entry>
              <hudson.model.Cause_-UpstreamCause>
                <upstreamProject>jenkins-job-generator-trigger</upstreamProject>
                <upstreamUrl>job/jenkins-job-generator-trigger/</upstreamUrl>
                <upstreamBuild>23</upstreamBuild>
                <upstreamCauses>
                  <hudson.triggers.SCMTrigger_-SCMTriggerCause />
                </upstreamCauses>
              </hudson.model.Cause_-UpstreamCause>
              <int>1</int>
            </entry>
          </causeBag>
        </hudson.model.CauseAction>
      </actions>
      <id>2085</id>
      <task class="org.jenkinsci.plugins.workflow.job.WorkflowJob">jenkins-job-generator</task>
      <inQueueSince>1630910835170</inQueueSince>
      <buildableStartMilliseconds>1630910844492</buildableStartMilliseconds>
      <outer-class>queue</outer-class>
    </hudson.model.Queue_-BlockedItem>
    <hudson.model.Queue_-BlockedItem>
      <actions>
        <hudson.model.CauseAction>
          <causeBag class="linked-hash-map">
            <entry>
              <org.jenkinsci.plugins.github.pullrequest.GitHubPRCause plugin="github-pullrequest@0.3.0">
                <skip>false</skip>
                <reason>PR opened</reason>
                <htmlUrl>https://github.com/SAP/SapMachine/pull/946</htmlUrl>
                <title>#895: Vitals: In SapMachine, we never shutdown the Vitals on VM exit (17)</title>
                <gitUrl>git://github.com/SAP/SapMachine.git</gitUrl>
                <sshUrl>git@github.com:SAP/SapMachine.git</sshUrl>
                <pollingLog>Running GitHub Pull Request trigger check for Sep 6, 2021, 12:35:00 PM on SAP/SapMachine
GitHub rate limit before check: GHRateLimit {core {remaining=4789, limit=5000, resetDate=Mon Sep 06 12:43:03 UTC 2021}, search {remaining=30, limit=30, resetDate=Mon Sep 06 12:36:00 UTC 2021}, graphql {remaining=5000, limit=5000, resetDate=Mon Sep 06 13:35:00 UTC 2021}, integrationManifest {remaining=5000, limit=5000, resetDate=Mon Sep 06 13:35:00 UTC 2021}}
No matching comments found for 946
Pull Request Opened: state has changed (PR was opened)
</pollingLog>
                <headSha>8dee5f0f9987abb0c4aa724865634288b8b6b08e</headSha>
                <number>946</number>
                <mergeable>false</mergeable>
                <targetBranch>sapmachine17</targetBranch>
                <sourceBranch>SapMachine-895-17</sourceBranch>
                <body>(cherry picked from commit e226ab1cab3f3b786d5bbcca7aa80a7b1397fc54)

Downported to 17

fixes #895 

</body>
                <sourceRepoOwner>tstuefe</sourceRepoOwner>
                <triggerSenderName>Thomas Stuefe</triggerSenderName>
                <labels />
                <commitAuthorName />
                <commitAuthorEmail />
                <condRef>head</condRef>
                <state>OPEN</state>
              </org.jenkinsci.plugins.github.pullrequest.GitHubPRCause>
              <int>1</int>
            </entry>
          </causeBag>
        </hudson.model.CauseAction>
        <hudson.model.ParametersAction>
          <safeParameters class="sorted-set">
            <string>BOOT_JDK_MAJOR</string>
            <string>BUILD_NUMBER</string>
            <string>EXTRA_CONFIGURE_OPTIONS</string>
            <string>GITHUB_PR_AUTHOR_EMAIL</string>
            <string>GITHUB_PR_BODY</string>
            <string>GITHUB_PR_CAUSE_SKIP</string>
            <string>GITHUB_PR_COMMENT_BODY</string>
            <string>GITHUB_PR_COMMENT_BODY_MATCH</string>
            <string>GITHUB_PR_COMMIT_AUTHOR_EMAIL</string>
            <string>GITHUB_PR_COMMIT_AUTHOR_NAME</string>
            <string>GITHUB_PR_COND_REF</string>
            <string>GITHUB_PR_HEAD_SHA</string>
            <string>GITHUB_PR_LABELS</string>
            <string>GITHUB_PR_NUMBER</string>
            <string>GITHUB_PR_SHORT_DESC</string>
            <string>GITHUB_PR_SOURCE_BRANCH</string>
            <string>GITHUB_PR_SOURCE_REPO_OWNER</string>
            <string>GITHUB_PR_STATE</string>
            <string>GITHUB_PR_TARGET_BRANCH</string>
            <string>GITHUB_PR_TITLE</string>
            <string>GITHUB_PR_TRIGGER_SENDER_AUTHOR</string>
            <string>GITHUB_PR_TRIGGER_SENDER_EMAIL</string>
            <string>GITHUB_PR_URL</string>
            <string>GITHUB_REPO_GIT_URL</string>
            <string>GITHUB_REPO_SSH_URL</string>
            <string>GIT_TAG_NAME</string>
            <string>PUBLISH</string>
            <string>RELEASE</string>
            <string>RUN_TESTS</string>
            <string>SAPMACHINE_ARCHIVE_NAME_PREFIX</string>
            <string>SAPMACHINE_GIT_BRANCH</string>
            <string>SAPMACHINE_GIT_REPOSITORY</string>
            <string>_CONFIGURE_SYSROOT</string>
            <string>hotspot_test_groups</string>
            <string>jdk_test_groups</string>
            <string>langtools_test_groups</string>
          </safeParameters>
          <parameters>
            <hudson.model.StringParameterValue>
              <name>SAPMACHINE_GIT_REPOSITORY</name>
              <description>The Git repository to use.</description>
              <value>https://github.com/SAP/SapMachine.git</value>
            </hudson.model.StringParameterValue>
            <hudson.model.StringParameterValue>
              <name>SAPMACHINE_GIT_BRANCH</name>
              <description>The Git branch to build.</description>
              <value>sapmachine17</value>
            </hudson.model.StringParameterValue>
            <hudson.model.StringParameterValue>
              <name>GIT_TAG_NAME</name>
              <description>The Git tag to build.</description>
              <value />
            </hudson.model.StringParameterValue>
            <hudson.model.StringParameterValue>
              <name>BUILD_NUMBER</name>
              <description>Sets the version build number explicitly.</description>
              <value />
            </hudson.model.StringParameterValue>
            <hudson.model.StringParameterValue>
              <name>SAPMACHINE_ARCHIVE_NAME_PREFIX</name>
              <description>The prefix of the bundle archive.</description>
              <value>sapmachine17-macos_aarch64</value>
            </hudson.model.StringParameterValue>
            <hudson.model.StringParameterValue>
              <name>_CONFIGURE_SYSROOT</name>
              <description>Sysroot configuration passed to configure script.</description>
              <value />
            </hudson.model.StringParameterValue>
            <hudson.model.StringParameterValue>
              <name>EXTRA_CONFIGURE_OPTIONS</name>
              <description>Configure options passed directly to configure script.</description>
              <value />
            </hudson.model.StringParameterValue>
            <hudson.model.StringParameterValue>
              <name>BOOT_JDK_MAJOR</name>
              <description>Specify the boot JDK major version explicitly.</description>
              <value />
            </hudson.model.StringParameterValue>
            <hudson.model.StringParameterValue>
              <name>hotspot_test_groups</name>
              <description>Select the test group for jtreg hotspot tests. Empty means disabled.</description>
              <value>:tier1</value>
            </hudson.model.StringParameterValue>
            <hudson.model.StringParameterValue>
              <name>jdk_test_groups</name>
              <description>Select the test group for jtreg jdk tests. Empty means disabled.</description>
              <value>:tier1</value>
            </hudson.model.StringParameterValue>
            <hudson.model.StringParameterValue>
              <name>langtools_test_groups</name>
              <description>Select the test group for jtreg langtools tests. Empty means disabled.</description>
              <value>"jdk tools lib"</value>
            </hudson.model.StringParameterValue>
            <hudson.model.BooleanParameterValue>
              <name>RUN_TESTS</name>
              <description>enable/disable jtreg runs</description>
              <value>true</value>
            </hudson.model.BooleanParameterValue>
            <hudson.model.BooleanParameterValue>
              <name>PUBLISH</name>
              <description>When set to true, the resulting bundles will be published to GitHub.</description>
              <value>false</value>
            </hudson.model.BooleanParameterValue>
            <hudson.model.BooleanParameterValue>
              <name>RELEASE</name>
              <description>When set to true, marks this build as a release build, otherwise as pre-release.</description>
              <value>false</value>
            </hudson.model.BooleanParameterValue>
            <hudson.model.StringParameterValue>
              <name>GITHUB_PR_TRIGGER_SENDER_AUTHOR</name>
              <value>Thomas Stuefe</value>
            </hudson.model.StringParameterValue>
            <hudson.model.StringParameterValue>
              <name>GITHUB_PR_TRIGGER_SENDER_EMAIL</name>
              <value />
            </hudson.model.StringParameterValue>
            <hudson.model.StringParameterValue>
              <name>GITHUB_PR_COMMIT_AUTHOR_NAME</name>
              <value />
            </hudson.model.StringParameterValue>
            <hudson.model.StringParameterValue>
              <name>GITHUB_PR_COMMIT_AUTHOR_EMAIL</name>
              <value />
            </hudson.model.StringParameterValue>
            <hudson.model.StringParameterValue>
              <name>GITHUB_PR_TARGET_BRANCH</name>
              <value>sapmachine17</value>
            </hudson.model.StringParameterValue>
            <hudson.model.StringParameterValue>
              <name>GITHUB_PR_SOURCE_BRANCH</name>
              <value>SapMachine-895-17</value>
            </hudson.model.StringParameterValue>
            <hudson.model.StringParameterValue>
              <name>GITHUB_PR_AUTHOR_EMAIL</name>
              <value />
            </hudson.model.StringParameterValue>
            <hudson.model.StringParameterValue>
              <name>GITHUB_PR_BODY</name>
              <value>(cherry picked from commit e226ab1cab3f3b786d5bbcca7aa80a7b1397fc54)\r\n\r\nDownported to 17\r\n\r\nfixes #895</value>
            </hudson.model.StringParameterValue>
            <hudson.model.StringParameterValue>
              <name>GITHUB_PR_SHORT_DESC</name>
              <value>GitHub PR #946: PR opened</value>
            </hudson.model.StringParameterValue>
            <hudson.model.StringParameterValue>
              <name>GITHUB_PR_TITLE</name>
              <value>#895: Vitals: In SapMachine, we never shutdown the Vitals on VM exit (17)</value>
            </hudson.model.StringParameterValue>
            <hudson.model.StringParameterValue>
              <name>GITHUB_PR_URL</name>
              <value>https://github.com/SAP/SapMachine/pull/946</value>
            </hudson.model.StringParameterValue>
            <hudson.model.StringParameterValue>
              <name>GITHUB_PR_SOURCE_REPO_OWNER</name>
              <value>tstuefe</value>
            </hudson.model.StringParameterValue>
            <hudson.model.StringParameterValue>
              <name>GITHUB_PR_HEAD_SHA</name>
              <value>8dee5f0f9987abb0c4aa724865634288b8b6b08e</value>
            </hudson.model.StringParameterValue>
            <hudson.model.StringParameterValue>
              <name>GITHUB_PR_COND_REF</name>
              <value>head</value>
            </hudson.model.StringParameterValue>
            <hudson.model.BooleanParameterValue>
              <name>GITHUB_PR_CAUSE_SKIP</name>
              <value>false</value>
            </hudson.model.BooleanParameterValue>
            <hudson.model.StringParameterValue>
              <name>GITHUB_PR_NUMBER</name>
              <value>946</value>
            </hudson.model.StringParameterValue>
            <hudson.model.StringParameterValue>
              <name>GITHUB_PR_STATE</name>
              <value>OPEN</value>
            </hudson.model.StringParameterValue>
            <hudson.model.StringParameterValue>
              <name>GITHUB_PR_COMMENT_BODY</name>
              <value />
            </hudson.model.StringParameterValue>
            <hudson.model.StringParameterValue>
              <name>GITHUB_PR_COMMENT_BODY_MATCH</name>
              <value />
            </hudson.model.StringParameterValue>
            <hudson.model.StringParameterValue>
              <name>GITHUB_PR_LABELS</name>
              <value />
            </hudson.model.StringParameterValue>
            <hudson.model.StringParameterValue>
              <name>GITHUB_REPO_GIT_URL</name>
              <value>git://github.com/SAP/SapMachine.git</value>
            </hudson.model.StringParameterValue>
            <hudson.model.StringParameterValue>
              <name>GITHUB_REPO_SSH_URL</name>
              <value>git@github.com:SAP/SapMachine.git</value>
            </hudson.model.StringParameterValue>
          </parameters>
        </hudson.model.ParametersAction>
        <org.jenkinsci.plugins.github.pullrequest.GitHubPRBadgeAction plugin="github-pullrequest@0.3.0">
          <htmlUrl>https://github.com/SAP/SapMachine/pull/946</htmlUrl>
          <title>#895: Vitals: In SapMachine, we never shutdown the Vitals on VM exit (17)</title>
          <number>946</number>
        </org.jenkinsci.plugins.github.pullrequest.GitHubPRBadgeAction>
      </actions>
      <id>2097</id>
      <task class="org.jenkinsci.plugins.workflow.job.WorkflowJob">build-17-pr-validation-macos_aarch64</task>
      <inQueueSince>1630931702373</inQueueSince>
      <buildableStartMilliseconds>1630931711756</buildableStartMilliseconds>
      <outer-class reference="../../hudson.model.Queue_-BlockedItem/outer-class" />
    </hudson.model.Queue_-BlockedItem>
    <hudson.model.Queue_-BuildableItem>
      <actions />
      <id>2083</id>
      <task class="org.jenkinsci.plugins.workflow.support.steps.ExecutorStepExecution$PlaceholderTask" plugin="workflow-durable-task-step@2.37">
        <context class="org.jenkinsci.plugins.workflow.cps.CpsStepContext" plugin="workflow-cps@2.90">
          <executionRef class="org.jenkinsci.plugins.workflow.job.WorkflowRun$Owner" plugin="workflow-job@2.40">
            <job>build-17-pr-validation-macos_aarch64</job>
            <id>13</id>
          </executionRef>
          <id>3</id>
          <bodyHeads />
          <body class="org.jenkinsci.plugins.workflow.cps.StaticBodyReference" resolves-to="org.jenkinsci.plugins.workflow.cps.HandleBodyReference">
            <id>1</id>
          </body>
          <threadId>0</threadId>
          <stepDescriptorId>org.jenkinsci.plugins.workflow.support.steps.ExecutorStep</stepDescriptorId>
        </context>
        <label>macos_aarch64</label>
        <runId>build-17-pr-validation-macos_aarch64#13</runId>
      </task>
      <inQueueSince>1630910367953</inQueueSince>
      <buildableStartMilliseconds>1630910367954</buildableStartMilliseconds>
      <isPending>false</isPending>
    </hudson.model.Queue_-BuildableItem>
  </items>
</hudson.model.Queue_-State>