<?xml version='1.1' encoding='UTF-8'?>
<hudson.model.Queue_-State>
  <counter>714</counter>
  <items>
    <hudson.model.Queue_-BuildableItem>
      <actions/>
      <id>713</id>
      <task class="org.jenkinsci.plugins.workflow.support.steps.ExecutorStepExecution$PlaceholderTask" plugin="workflow-durable-task-step@2.29">
        <context class="org.jenkinsci.plugins.workflow.cps.CpsStepContext" plugin="workflow-cps@2.65">
          <executionRef class="org.jenkinsci.plugins.workflow.job.WorkflowRun$Owner" plugin="workflow-job@2.32">
            <job>build-11-release-macos_x86_64</job>
            <id>10</id>
          </executionRef>
          <id>3</id>
          <bodyHeads/>
          <body class="org.jenkinsci.plugins.workflow.cps.StaticBodyReference" resolves-to="org.jenkinsci.plugins.workflow.cps.HandleBodyReference">
            <id>1</id>
          </body>
          <threadId>0</threadId>
          <stepDescriptorId>org.jenkinsci.plugins.workflow.support.steps.ExecutorStep</stepDescriptorId>
        </context>
        <label>macos_x86_64</label>
        <runId>build-11-release-macos_x86_64#10</runId>
      </task>
      <inQueueSince>1554340155298</inQueueSince>
      <buildableStartMilliseconds>1554340155298</buildableStartMilliseconds>
      <isPending>false</isPending>
    </hudson.model.Queue_-BuildableItem>
  </items>
</hudson.model.Queue_-State>